pyfactorybridge/__init__.py
pyfactorybridge/__main__.py
pyfactorybridge/authentication.py
pyfactorybridge/exceptions.py
pyfactorybridge/ssl_adapter.py
pyfactorybridge-1.0.1.dist-info/LICENSE
pyfactorybridge-1.0.1.dist-info/METADATA
pyfactorybridge-1.0.1.dist-info/WHEEL
pyfactorybridge-1.0.1.dist-info/RECORD
