Metadata-Version: 2.1
Name: pyfactorybridge
Version: 1.0.1
Summary: Wrapper around the Satisfactory Dedicated Server HTTP API
License: MIT
Author: Jayy001
Author-email: github@skii.dev
Requires-Python: >=3.8,<4.0
Classifier: License :: OSI Approved :: MIT License
Classifier: Programming Language :: Python :: 3
Classifier: Programming Language :: Python :: 3.8
Classifier: Programming Language :: Python :: 3.9
Classifier: Programming Language :: Python :: 3.10
Classifier: Programming Language :: Python :: 3.11
Classifier: Programming Language :: Python :: 3.12
Requires-Dist: requests (>=2.32.3,<3.0.0)
Requires-Dist: typing_extensions (>=4.12.0,<5.0.0)
